cythonanyarray/README.MD
cythonanyarray/__init__.py
cythonanyarray/requirements.txt
cythonanyarray/thirdparty.json
cythonanyarray-0.10.dist-info/LICENSE.rst
cythonanyarray-0.10.dist-info/METADATA
cythonanyarray-0.10.dist-info/WHEEL
cythonanyarray-0.10.dist-info/top_level.txt
cythonanyarray-0.10.dist-info/RECORD
