Metadata-Version: 2.1
Name: cythonanyarray
Version: 0.10
Summary: Pass arrays of any dimension to Cython as memory views (no Global Interpreter Lock (GIL))
Home-page: https://github.com/hansalemaos/cythonanyarray
Author: Johannes Fischer
Author-email: aulasparticularesdealemaosp@gmail.com
License: MIT
Keywords: cython,arrays
Classifier: Development Status :: 4 - Beta
Classifier: Programming Language :: Python :: 3 :: Only
Classifier: Programming Language :: Python :: 3.10
Classifier: Topic :: Software Development :: Libraries :: Python Modules
Classifier: Topic :: Utilities
License-File: LICENSE.rst
Requires-Dist: Cython
Requires-Dist: numexpr
Requires-Dist: numpy
